{"width":2048,"SubTexture":[{"width":486,"y":428,"height":154,"name":"touying","x":577},{"width":97,"y":1,"height":154,"name":"zhengchang_(shang_)","x":1939},{"width":84,"y":584,"height":94,"name":"zhengchang(xiabi)","x":577},{"width":116,"y":717,"height":89,"name":"zhengchangshou(zuo)","x":1308},{"width":329,"y":709,"height":278,"name":"xiaobianzi","x":1},{"width":121,"y":717,"height":233,"name":"liuhai04","x":1185},{"width":119,"y":1,"height":132,"name":"shoubizuo（aishang）","x":1518},{"width":275,"y":1,"height":425,"name":"tuibu","x":577},{"width":231,"y":584,"height":186,"name":"shenti","x":824},{"width":574,"y":1,"height":706,"name":"naodai","x":1},{"width":358,"y":246,"height":142,"name":"yanjing（zhengchang）","x":854},{"width":359,"y":1,"height":136,"name":"yanjing（sikao）","x":1157},{"width":318,"y":584,"height":131,"name":"yanjing（tiaopi）","x":1057},{"width":359,"y":772,"height":119,"name":"yanjing（fanu）","x":824},{"width":346,"y":139,"height":89,"name":"yanjing（biyan）","x":1157},{"width":343,"y":893,"height":89,"name":"yanjing（aishang）","x":824},{"width":99,"y":1,"height":160,"name":"shoubi（you）（zhengchang）","x":1838},{"width":91,"y":724,"height":121,"name":"zhengchangshou(xia_)","x":1921},{"width":127,"y":717,"height":76,"name":"zhengchangshou(you)","x":1429},{"width":75,"y":741,"height":104,"name":"shoubi（you）（aishang）","x":1836},{"width":77,"y":847,"height":142,"name":"shoubi（shang）（aishang）（zuo）","x":1921},{"width":123,"y":1,"height":127,"name":"shoubi（shang）（aishang）（you）","x":1639},{"width":119,"y":808,"height":85,"name":"shoubi（nu）","x":1308},{"width":67,"y":464,"height":57,"name":"shou（nu）","x":1913},{"width":72,"y":157,"height":65,"name":"zui（kaixin）","x":1975},{"width":166,"y":527,"height":73,"name":"zui（fanu）","x":1836},{"width":92,"y":991,"height":16,"name":"zui（sikao）","x":1836},{"width":135,"y":163,"height":57,"name":"zui（aishang）","x":1838},{"width":72,"y":717,"height":46,"name":"zuiba（zhongjianzhen）","x":1057},{"width":66,"y":680,"height":16,"name":"zuiba（bihe）（zhengchang）","x":577},{"width":80,"y":847,"height":66,"name":"shou（aishang）（zuo）","x":1836},{"width":72,"y":915,"height":72,"name":"shou（aishang）（you）","x":1836},{"width":92,"y":602,"height":120,"name":"shoubi（sikao）","x":1921},{"width":118,"y":363,"height":99,"name":"shou（sikao）","x":1913},{"width":331,"y":139,"height":49,"name":"meimao（zhengchang）","x":1505},{"width":315,"y":952,"height":68,"name":"meimao（aishang）","x":1185},{"width":29,"y":717,"height":44,"name":"yanlei02","x":1131},{"width":29,"y":464,"height":44,"name":"yanlei01","x":1982},{"width":332,"y":952,"height":57,"name":"meimao（nu，sikao）","x":1502},{"width":155,"y":584,"height":408,"name":"liuhai03","x":667},{"width":75,"y":363,"height":162,"name":"shoubi（tiaopi）","x":1836},{"width":83,"y":602,"height":137,"name":"shou（tiaopi）","x":1836},{"width":301,"y":1,"height":243,"name":"liuhai02","x":854},{"width":333,"y":709,"height":272,"name":"liuhai01","x":332},{"width":142,"y":230,"height":131,"name":"nu_","x":1836}],"height":1024,"name":"nv_2","imagePath":"nv_2_tex.png"}