{"frameRate":24,"armature":[{"bone":[{"name":"root","transform":{}},{"length":152,"transform":{"y":-102,"x":-377.7},"parent":"root","name":"youchuan"}],"ik":[],"skin":[{"name":"","slot":[{"display":[{"path":"youchuan","type":"image","name":"游船","transform":{"y":-11,"x":72.7}}],"name":"youchuan"},{"display":[{"path":"bowen","type":"image","name":"图层_49_副本","transform":{"y":8.5,"x":51.7}}],"name":"bowen"},{"display":[{"path":"bowen_2","type":"image","name":"图层_49","transform":{"y":10.5,"x":41.7}}],"name":"bowen_2"}]}],"aabb":{"width":240.0000000000001,"y":-145.99999999999977,"height":66.00000000000001,"x":-452},"type":"Armature","frameRate":24,"defaultActions":[{"gotoAndPlay":"newAnimation"}],"slot":[{"name":"youchuan","parent":"youchuan","color":{}},{"z":1,"name":"bowen_2","parent":"youchuan","color":{}},{"z":2,"name":"bowen","parent":"youchuan","color":{}}],"animation":[{"bone":[{"frame":[{"duration":1000,"tweenEasing":null,"transform":{}}],"name":"root"},{"frame":[{"duration":1000,"tweenEasing":0,"transform":{"scX":0.8,"scY":0.8,"x":-730.9712}},{"duration":0,"tweenEasing":null,"transform":{"x":1294.1477}}],"name":"youchuan"}],"slot":[{"frame":[{"duration":5,"tweenEasing":0},{"displayIndex":-1,"duration":5,"tweenEasing":0},{"duration":5,"tweenEasing":0},{"displayIndex":-1,"duration":5,"tweenEasing":0},{"duration":5,"tweenEasing":0},{"displayIndex":-1,"duration":5,"tweenEasing":0},{"duration":5,"tweenEasing":0},{"displayIndex":-1,"duration":5,"tweenEasing":0},{"duration":5,"tweenEasing":0},{"displayIndex":-1,"duration":5,"tweenEasing":0},{"duration":5,"tweenEasing":0},{"displayIndex":-1,"duration":5,"tweenEasing":0},{"duration":5,"tweenEasing":0},{"displayIndex":-1,"duration":5,"tweenEasing":0},{"duration":5,"tweenEasing":0},{"displayIndex":-1,"duration":5,"tweenEasing":0},{"duration":5,"tweenEasing":0},{"displayIndex":-1,"duration":5,"tweenEasing":0},{"duration":5,"tweenEasing":0},{"displayIndex":-1,"duration":5,"tweenEasing":0},{"duration":5,"tweenEasing":0},{"displayIndex":-1,"duration":5,"tweenEasing":0},{"duration":5,"tweenEasing":0},{"displayIndex":-1,"duration":5,"tweenEasing":0},{"duration":5,"tweenEasing":0},{"displayIndex":-1,"duration":5,"tweenEasing":0},{"duration":5,"tweenEasing":0},{"displayIndex":-1,"duration":5,"tweenEasing":0},{"duration":5,"tweenEasing":0},{"displayIndex":-1,"duration":5,"tweenEasing":0},{"duration":5,"tweenEasing":0},{"displayIndex":-1,"duration":5,"tweenEasing":0},{"duration":5,"tweenEasing":0},{"displayIndex":-1,"duration":5,"tweenEasing":0},{"duration":5,"tweenEasing":0},{"displayIndex":-1,"duration":5,"tweenEasing":0},{"duration":5,"tweenEasing":0},{"displayIndex":-1,"duration":5,"tweenEasing":0},{"duration":5,"tweenEasing":0},{"displayIndex":-1,"duration":5,"tweenEasing":0},{"duration":5,"tweenEasing":0},{"displayIndex":-1,"duration":5,"tweenEasing":0},{"duration":5,"tweenEasing":0},{"displayIndex":-1,"duration":5,"tweenEasing":0},{"duration":5,"tweenEasing":0},{"displayIndex":-1,"duration":5,"tweenEasing":0},{"duration":5,"tweenEasing":0},{"displayIndex":-1,"duration":5,"tweenEasing":0},{"duration":5,"tweenEasing":0},{"displayIndex":-1,"duration":5,"tweenEasing":0},{"duration":5,"tweenEasing":0},{"displayIndex":-1,"duration":5,"tweenEasing":0},{"duration":5,"tweenEasing":0},{"displayIndex":-1,"duration":5,"tweenEasing":0},{"duration":5,"tweenEasing":0},{"displayIndex":-1,"duration":5,"tweenEasing":0},{"duration":5,"tweenEasing":0},{"displayIndex":-1,"duration":5,"tweenEasing":0},{"duration":5,"tweenEasing":0},{"displayIndex":-1,"duration":5,"tweenEasing":0},{"duration":5,"tweenEasing":0},{"displayIndex":-1,"duration":5,"tweenEasing":0},{"duration":5,"tweenEasing":0},{"displayIndex":-1,"duration":5,"tweenEasing":0},{"duration":5,"tweenEasing":0},{"displayIndex":-1,"duration":5,"tweenEasing":0},{"duration":5,"tweenEasing":0},{"displayIndex":-1,"duration":5,"tweenEasing":0},{"duration":5,"tweenEasing":0},{"displayIndex":-1,"duration":5,"tweenEasing":0},{"duration":5,"tweenEasing":0},{"displayIndex":-1,"duration":5,"tweenEasing":0},{"duration":5,"tweenEasing":0},{"displayIndex":-1,"duration":5,"tweenEasing":0},{"duration":5,"tweenEasing":0},{"displayIndex":-1,"duration":5,"tweenEasing":0},{"duration":5,"tweenEasing":0},{"displayIndex":-1,"duration":5,"tweenEasing":0},{"duration":5,"tweenEasing":0},{"displayIndex":-1,"duration":5,"tweenEasing":0},{"duration":5,"tweenEasing":0},{"displayIndex":-1,"duration":5,"tweenEasing":0},{"duration":5,"tweenEasing":0},{"displayIndex":-1,"duration":5,"tweenEasing":0},{"duration":5,"tweenEasing":0},{"displayIndex":-1,"duration":5,"tweenEasing":0},{"duration":5,"tweenEasing":0},{"displayIndex":-1,"duration":5,"tweenEasing":0},{"duration":5,"tweenEasing":0},{"displayIndex":-1,"duration":5,"tweenEasing":0},{"duration":5,"tweenEasing":0},{"displayIndex":-1,"duration":5,"tweenEasing":0},{"duration":5,"tweenEasing":0},{"displayIndex":-1,"duration":5,"tweenEasing":0},{"duration":5,"tweenEasing":0},{"displayIndex":-1,"duration":5,"tweenEasing":0},{"duration":5,"tweenEasing":0},{"displayIndex":-1,"duration":5,"tweenEasing":0},{"duration":5,"tweenEasing":0},{"displayIndex":-1,"duration":5,"tweenEasing":0},{"duration":5,"tweenEasing":0},{"displayIndex":-1,"duration":5,"tweenEasing":0},{"duration":5,"tweenEasing":0},{"displayIndex":-1,"duration":5,"tweenEasing":0},{"duration":5,"tweenEasing":0},{"displayIndex":-1,"duration":5,"tweenEasing":0},{"duration":5,"tweenEasing":0},{"displayIndex":-1,"duration":5,"tweenEasing":0},{"duration":5,"tweenEasing":0},{"displayIndex":-1,"duration":5,"tweenEasing":0},{"duration":5,"tweenEasing":0},{"displayIndex":-1,"duration":5,"tweenEasing":0},{"duration":5,"tweenEasing":0},{"displayIndex":-1,"duration":5,"tweenEasing":0},{"duration":5,"tweenEasing":0},{"displayIndex":-1,"duration":5,"tweenEasing":0},{"duration":5,"tweenEasing":0},{"displayIndex":-1,"duration":5,"tweenEasing":0},{"duration":5,"tweenEasing":0},{"displayIndex":-1,"duration":5,"tweenEasing":0},{"duration":5,"tweenEasing":0},{"displayIndex":-1,"duration":5,"tweenEasing":0},{"duration":5,"tweenEasing":0},{"displayIndex":-1,"duration":5,"tweenEasing":0},{"duration":5,"tweenEasing":0},{"displayIndex":-1,"duration":5,"tweenEasing":0},{"duration":5,"tweenEasing":0},{"displayIndex":-1,"duration":5,"tweenEasing":0},{"duration":5,"tweenEasing":0},{"displayIndex":-1,"duration":5,"tweenEasing":0},{"duration":5,"tweenEasing":0},{"displayIndex":-1,"duration":5,"tweenEasing":0},{"duration":5,"tweenEasing":0},{"displayIndex":-1,"duration":5,"tweenEasing":0},{"duration":5,"tweenEasing":0},{"displayIndex":-1,"duration":5,"tweenEasing":0},{"duration":5,"tweenEasing":0},{"displayIndex":-1,"duration":5,"tweenEasing":0},{"duration":5,"tweenEasing":0},{"displayIndex":-1,"duration":5,"tweenEasing":0},{"duration":5,"tweenEasing":0},{"displayIndex":-1,"duration":5,"tweenEasing":0},{"duration":5,"tweenEasing":0},{"displayIndex":-1,"duration":5,"tweenEasing":0},{"duration":5,"tweenEasing":0},{"displayIndex":-1,"duration":5,"tweenEasing":0},{"duration":5,"tweenEasing":0},{"displayIndex":-1,"duration":5,"tweenEasing":0},{"duration":5,"tweenEasing":0},{"displayIndex":-1,"duration":5,"tweenEasing":0},{"duration":5,"tweenEasing":0},{"displayIndex":-1,"duration":5,"tweenEasing":0},{"duration":5,"tweenEasing":0},{"displayIndex":-1,"duration":5,"tweenEasing":0},{"duration":5,"tweenEasing":0},{"displayIndex":-1,"duration":5,"tweenEasing":0},{"duration":5,"tweenEasing":0},{"displayIndex":-1,"duration":5,"tweenEasing":0},{"duration":5,"tweenEasing":0},{"displayIndex":-1,"duration":5,"tweenEasing":0},{"duration":5,"tweenEasing":0},{"displayIndex":-1,"duration":5,"tweenEasing":0},{"duration":5,"tweenEasing":0},{"displayIndex":-1,"duration":5,"tweenEasing":0},{"duration":5,"tweenEasing":0},{"displayIndex":-1,"duration":5,"tweenEasing":0},{"duration":5,"tweenEasing":0},{"displayIndex":-1,"duration":5,"tweenEasing":0},{"duration":5,"tweenEasing":0},{"displayIndex":-1,"duration":5,"tweenEasing":0},{"duration":5,"tweenEasing":0},{"displayIndex":-1,"duration":5,"tweenEasing":0},{"duration":5,"tweenEasing":0},{"displayIndex":-1,"duration":5,"tweenEasing":0},{"duration":5,"tweenEasing":0},{"displayIndex":-1,"duration":5,"tweenEasing":0},{"duration":5,"tweenEasing":0},{"displayIndex":-1,"duration":5,"tweenEasing":0},{"duration":5,"tweenEasing":0},{"displayIndex":-1,"duration":5,"tweenEasing":0},{"duration":5,"tweenEasing":0},{"displayIndex":-1,"duration":5,"tweenEasing":0},{"duration":5,"tweenEasing":0},{"displayIndex":-1,"duration":5,"tweenEasing":0},{"duration":5,"tweenEasing":0},{"displayIndex":-1,"duration":5,"tweenEasing":0},{"duration":5,"tweenEasing":0},{"displayIndex":-1,"duration":5,"tweenEasing":0},{"duration":5,"tweenEasing":0},{"displayIndex":-1,"duration":5,"tweenEasing":0},{"duration":5,"tweenEasing":0},{"displayIndex":-1,"duration":5,"tweenEasing":0},{"duration":5,"tweenEasing":0},{"displayIndex":-1,"duration":5,"tweenEasing":0},{"duration":5,"tweenEasing":0},{"displayIndex":-1,"duration":5,"tweenEasing":0},{"duration":5,"tweenEasing":0},{"displayIndex":-1,"duration":5,"tweenEasing":0},{"duration":5,"tweenEasing":0},{"displayIndex":-1,"duration":5,"tweenEasing":0},{"duration":0,"tweenEasing":null}],"name":"bowen_2"},{"frame":[{"displayIndex":-1,"duration":5,"tweenEasing":0},{"duration":5,"tweenEasing":0},{"displayIndex":-1,"duration":5,"tweenEasing":0},{"duration":5,"tweenEasing":0},{"displayIndex":-1,"duration":5,"tweenEasing":0},{"duration":5,"tweenEasing":0},{"displayIndex":-1,"duration":5,"tweenEasing":0},{"duration":5,"tweenEasing":0},{"displayIndex":-1,"duration":5,"tweenEasing":0},{"duration":5,"tweenEasing":0},{"displayIndex":-1,"duration":5,"tweenEasing":0},{"duration":5,"tweenEasing":0},{"displayIndex":-1,"duration":5,"tweenEasing":0},{"duration":5,"tweenEasing":0},{"displayIndex":-1,"duration":5,"tweenEasing":0},{"duration":5,"tweenEasing":0},{"displayIndex":-1,"duration":5,"tweenEasing":0},{"duration":5,"tweenEasing":0},{"displayIndex":-1,"duration":5,"tweenEasing":0},{"duration":5,"tweenEasing":0},{"displayIndex":-1,"duration":5,"tweenEasing":0},{"duration":5,"tweenEasing":0},{"displayIndex":-1,"duration":5,"tweenEasing":0},{"duration":5,"tweenEasing":0},{"displayIndex":-1,"duration":5,"tweenEasing":0},{"duration":5,"tweenEasing":0},{"displayIndex":-1,"duration":5,"tweenEasing":0},{"duration":5,"tweenEasing":0},{"displayIndex":-1,"duration":5,"tweenEasing":0},{"duration":5,"tweenEasing":0},{"displayIndex":-1,"duration":5,"tweenEasing":0},{"duration":5,"tweenEasing":0},{"displayIndex":-1,"duration":5,"tweenEasing":0},{"duration":5,"tweenEasing":0},{"displayIndex":-1,"duration":5,"tweenEasing":0},{"duration":5,"tweenEasing":0},{"displayIndex":-1,"duration":5,"tweenEasing":0},{"duration":5,"tweenEasing":0},{"displayIndex":-1,"duration":5,"tweenEasing":0},{"duration":5,"tweenEasing":0},{"displayIndex":-1,"duration":5,"tweenEasing":0},{"duration":5,"tweenEasing":0},{"displayIndex":-1,"duration":5,"tweenEasing":0},{"duration":5,"tweenEasing":0},{"displayIndex":-1,"duration":5,"tweenEasing":0},{"duration":5,"tweenEasing":0},{"displayIndex":-1,"duration":5,"tweenEasing":0},{"duration":5,"tweenEasing":0},{"displayIndex":-1,"duration":5,"tweenEasing":0},{"duration":5,"tweenEasing":0},{"displayIndex":-1,"duration":5,"tweenEasing":0},{"duration":5,"tweenEasing":0},{"displayIndex":-1,"duration":5,"tweenEasing":0},{"duration":5,"tweenEasing":0},{"displayIndex":-1,"duration":5,"tweenEasing":0},{"duration":5,"tweenEasing":0},{"displayIndex":-1,"duration":5,"tweenEasing":0},{"duration":5,"tweenEasing":0},{"displayIndex":-1,"duration":5,"tweenEasing":0},{"duration":5,"tweenEasing":0},{"displayIndex":-1,"duration":5,"tweenEasing":0},{"duration":5,"tweenEasing":0},{"displayIndex":-1,"duration":5,"tweenEasing":0},{"duration":5,"tweenEasing":0},{"displayIndex":-1,"duration":5,"tweenEasing":0},{"duration":5,"tweenEasing":0},{"displayIndex":-1,"duration":5,"tweenEasing":0},{"duration":5,"tweenEasing":0},{"displayIndex":-1,"duration":5,"tweenEasing":0},{"duration":5,"tweenEasing":0},{"displayIndex":-1,"duration":5,"tweenEasing":0},{"duration":5,"tweenEasing":0},{"displayIndex":-1,"duration":5,"tweenEasing":0},{"duration":5,"tweenEasing":0},{"displayIndex":-1,"duration":5,"tweenEasing":0},{"duration":5,"tweenEasing":0},{"displayIndex":-1,"duration":5,"tweenEasing":0},{"duration":5,"tweenEasing":0},{"displayIndex":-1,"duration":5,"tweenEasing":0},{"duration":5,"tweenEasing":0},{"displayIndex":-1,"duration":5,"tweenEasing":0},{"duration":5,"tweenEasing":0},{"displayIndex":-1,"duration":5,"tweenEasing":0},{"duration":5,"tweenEasing":0},{"displayIndex":-1,"duration":5,"tweenEasing":0},{"duration":5,"tweenEasing":0},{"displayIndex":-1,"duration":5,"tweenEasing":0},{"duration":5,"tweenEasing":0},{"displayIndex":-1,"duration":5,"tweenEasing":0},{"duration":5,"tweenEasing":0},{"displayIndex":-1,"duration":5,"tweenEasing":0},{"duration":5,"tweenEasing":0},{"displayIndex":-1,"duration":5,"tweenEasing":0},{"duration":5,"tweenEasing":0},{"displayIndex":-1,"duration":5,"tweenEasing":0},{"duration":5,"tweenEasing":0},{"displayIndex":-1,"duration":5,"tweenEasing":0},{"duration":5,"tweenEasing":0},{"displayIndex":-1,"duration":5,"tweenEasing":0},{"duration":5,"tweenEasing":0},{"displayIndex":-1,"duration":5,"tweenEasing":0},{"duration":5,"tweenEasing":0},{"displayIndex":-1,"duration":5,"tweenEasing":0},{"duration":5,"tweenEasing":0},{"displayIndex":-1,"duration":5,"tweenEasing":0},{"duration":5,"tweenEasing":0},{"displayIndex":-1,"duration":5,"tweenEasing":0},{"duration":5,"tweenEasing":0},{"displayIndex":-1,"duration":5,"tweenEasing":0},{"duration":5,"tweenEasing":0},{"displayIndex":-1,"duration":5,"tweenEasing":0},{"duration":5,"tweenEasing":0},{"displayIndex":-1,"duration":5,"tweenEasing":0},{"duration":5,"tweenEasing":0},{"displayIndex":-1,"duration":5,"tweenEasing":0},{"duration":5,"tweenEasing":0},{"displayIndex":-1,"duration":5,"tweenEasing":0},{"duration":5,"tweenEasing":0},{"displayIndex":-1,"duration":5,"tweenEasing":0},{"duration":5,"tweenEasing":0},{"displayIndex":-1,"duration":5,"tweenEasing":0},{"duration":5,"tweenEasing":0},{"displayIndex":-1,"duration":5,"tweenEasing":0},{"duration":5,"tweenEasing":0},{"displayIndex":-1,"duration":5,"tweenEasing":0},{"duration":5,"tweenEasing":0},{"displayIndex":-1,"duration":5,"tweenEasing":0},{"duration":5,"tweenEasing":0},{"displayIndex":-1,"duration":5,"tweenEasing":0},{"duration":5,"tweenEasing":0},{"displayIndex":-1,"duration":5,"tweenEasing":0},{"duration":5,"tweenEasing":0},{"displayIndex":-1,"duration":5,"tweenEasing":0},{"duration":5,"tweenEasing":0},{"displayIndex":-1,"duration":5,"tweenEasing":0},{"duration":5,"tweenEasing":0},{"displayIndex":-1,"duration":5,"tweenEasing":0},{"duration":5,"tweenEasing":0},{"displayIndex":-1,"duration":5,"tweenEasing":0},{"duration":5,"tweenEasing":0},{"displayIndex":-1,"duration":5,"tweenEasing":0},{"duration":5,"tweenEasing":0},{"displayIndex":-1,"duration":5,"tweenEasing":0},{"duration":5,"tweenEasing":0},{"displayIndex":-1,"duration":5,"tweenEasing":0},{"duration":5,"tweenEasing":0},{"displayIndex":-1,"duration":5,"tweenEasing":0},{"duration":5,"tweenEasing":0},{"displayIndex":-1,"duration":5,"tweenEasing":0},{"duration":5,"tweenEasing":0},{"displayIndex":-1,"duration":5,"tweenEasing":0},{"duration":5,"tweenEasing":0},{"displayIndex":-1,"duration":5,"tweenEasing":0},{"duration":5,"tweenEasing":0},{"displayIndex":-1,"duration":5,"tweenEasing":0},{"duration":5,"tweenEasing":0},{"displayIndex":-1,"duration":5,"tweenEasing":0},{"duration":5,"tweenEasing":0},{"displayIndex":-1,"duration":5,"tweenEasing":0},{"duration":5,"tweenEasing":0},{"displayIndex":-1,"duration":5,"tweenEasing":0},{"duration":5,"tweenEasing":0},{"displayIndex":-1,"duration":5,"tweenEasing":0},{"duration":5,"tweenEasing":0},{"displayIndex":-1,"duration":5,"tweenEasing":0},{"duration":5,"tweenEasing":0},{"displayIndex":-1,"duration":5,"tweenEasing":0},{"duration":5,"tweenEasing":0},{"displayIndex":-1,"duration":5,"tweenEasing":0},{"duration":5,"tweenEasing":0},{"displayIndex":-1,"duration":5,"tweenEasing":0},{"duration":5,"tweenEasing":0},{"displayIndex":-1,"duration":5,"tweenEasing":0},{"duration":5,"tweenEasing":0},{"displayIndex":-1,"duration":5,"tweenEasing":0},{"duration":5,"tweenEasing":0},{"displayIndex":-1,"duration":5,"tweenEasing":0},{"duration":5,"tweenEasing":0},{"displayIndex":-1,"duration":5,"tweenEasing":0},{"duration":5,"tweenEasing":0},{"displayIndex":-1,"duration":5,"tweenEasing":0},{"duration":5,"tweenEasing":0},{"displayIndex":-1,"duration":5,"tweenEasing":0},{"duration":5,"tweenEasing":0},{"displayIndex":-1,"duration":5,"tweenEasing":0},{"duration":5,"tweenEasing":0},{"displayIndex":-1,"duration":5,"tweenEasing":0},{"duration":5,"tweenEasing":0},{"displayIndex":-1,"duration":5,"tweenEasing":0},{"duration":5,"tweenEasing":0},{"displayIndex":-1,"duration":5,"tweenEasing":0},{"duration":5,"tweenEasing":0},{"displayIndex":-1,"duration":5,"tweenEasing":0},{"duration":5,"tweenEasing":0},{"displayIndex":-1,"duration":5,"tweenEasing":0},{"duration":5,"tweenEasing":0},{"displayIndex":-1,"duration":5,"tweenEasing":0},{"duration":5,"tweenEasing":0},{"displayIndex":-1,"duration":5,"tweenEasing":0},{"duration":5,"tweenEasing":0},{"displayIndex":-1,"duration":0,"tweenEasing":null}],"name":"bowen"}],"frame":[],"ffd":[],"playTimes":0,"duration":1000,"name":"newAnimation"}],"name":"armatureName"}],"isGlobal":0,"name":"dengrujiemian","version":"5.0"}