{"frameRate":30,"armature":[{"ik":[],"type":"Armature","name":"armatureName","skin":[{"slot":[{"display":[{"path":"K","type":"image","name":"图层_670_拷贝","transform":{"y":-7.6483,"skX":91.8214,"skY":91.8214,"x":33.2099}}],"name":"K"},{"display":[{"path":"J","type":"image","name":"图层_670_拷贝_3","transform":{"y":-4.7169,"skX":134.5489,"skY":134.5489,"x":33.2686}}],"name":"J"},{"display":[{"path":"dou","type":"image","name":"字_拷贝_5","transform":{"y":-8,"skX":90,"skY":90,"x":15.3}}],"name":"dou"},{"display":[{"path":"Q","type":"image","name":"图层_670_拷贝_2","transform":{"y":-9.9171,"skX":110.1448,"skY":110.1448,"x":35.5395}}],"name":"Q"},{"display":[{"path":"di","type":"image","name":"字_拷贝_4","transform":{"y":-1.2,"skX":90,"skY":90,"x":15.3}}],"name":"di"},{"display":[{"path":"BG","type":"image","name":"组_32","transform":{"y":5}}],"name":"BG"},{"display":[{"path":"zhu","type":"image","name":"字","transform":{"y":-0.9,"skX":90,"skY":90,"x":15}}],"name":"zhu"},{"display":[{"path":"A","type":"image","name":"图层_670","transform":{"y":2.6114,"skX":76.9838,"skY":76.9838,"x":41.7611}}],"name":"A"}],"name":""}],"aabb":{"width":304,"y":-108,"height":226,"x":-152},"slot":[{"name":"BG","parent":"root","color":{}},{"z":1,"name":"J","parent":"J","color":{}},{"z":2,"name":"Q","parent":"Q","color":{}},{"z":3,"name":"K","parent":"K","color":{}},{"z":4,"name":"A","parent":"A","color":{}},{"z":5,"name":"zhu","parent":"zhu","color":{}},{"z":6,"name":"di","parent":"di","color":{}},{"z":7,"name":"dou","parent":"dou","color":{}}],"animation":[{"ffd":[],"frame":[],"playTimes":0,"slot":[],"duration":60,"name":"newAnimation","bone":[{"frame":[{"duration":60,"tweenEasing":null,"transform":{}}],"name":"root"},{"frame":[{"duration":30,"tweenEasing":0,"transform":{}},{"duration":30,"tweenEasing":0,"transform":{"scX":1.08,"y":-6.3278,"scY":1.08}},{"duration":0,"tweenEasing":null,"transform":{}}],"name":"dou"},{"frame":[{"duration":30,"tweenEasing":0,"transform":{}},{"duration":30,"tweenEasing":0,"transform":{"scX":1.08,"y":-6.3278,"scY":1.08}},{"duration":0,"tweenEasing":null,"transform":{}}],"name":"di"},{"frame":[{"duration":30,"tweenEasing":0,"transform":{}},{"duration":30,"tweenEasing":0,"transform":{"scX":1.0778,"y":-6.3278,"scY":1.0778}},{"duration":0,"tweenEasing":null,"transform":{}}],"name":"zhu"},{"frame":[{"duration":30,"tweenEasing":0,"transform":{}},{"duration":30,"tweenEasing":0,"transform":{"y":-1.1331,"skX":-5.1408,"skY":-5.1408}},{"duration":0,"tweenEasing":null,"transform":{}}],"name":"J"},{"frame":[{"duration":30,"tweenEasing":0,"transform":{}},{"duration":30,"tweenEasing":0,"transform":{"y":-4.6496,"skX":-2.5951,"skY":-2.5951,"x":-5}},{"duration":0,"tweenEasing":null,"transform":{}}],"name":"Q"},{"frame":[{"duration":30,"tweenEasing":0,"transform":{}},{"duration":30,"tweenEasing":0,"transform":{"y":-8.2161,"skX":0.6576,"skY":0.6576}},{"duration":0,"tweenEasing":null,"transform":{}}],"name":"K"},{"frame":[{"duration":30,"tweenEasing":0,"transform":{}},{"duration":30,"tweenEasing":0,"transform":{"y":-1.1331,"skX":7.2911,"skY":7.2911}},{"duration":0,"tweenEasing":null,"transform":{}}],"name":"A"}]}],"frameRate":30,"defaultActions":[{"gotoAndPlay":"newAnimation"}],"bone":[{"name":"root","transform":{}},{"length":43,"transform":{"y":64.3,"skX":-90,"skY":-90,"x":-44.5},"parent":"root","name":"dou"},{"length":76,"transform":{"y":9.9,"skX":-134.5489,"skY":-134.5489,"x":-13.3},"parent":"root","name":"J"},{"length":42,"transform":{"y":64,"skX":-90,"skY":-90,"x":50.4},"parent":"root","name":"zhu"},{"length":84,"transform":{"y":3.95,"skX":-110.1448,"skY":-110.1448,"x":-5.95},"parent":"root","name":"Q"},{"length":43,"transform":{"y":64.3,"skX":-90,"skY":-90,"x":-0.3},"parent":"root","name":"di"},{"length":99,"transform":{"y":7.1,"skX":-76.9838,"skY":-76.9838,"x":24.05},"parent":"root","name":"A"},{"length":88,"transform":{"y":3.95,"skX":-91.8214,"skY":-91.8214,"x":6.2},"parent":"root","name":"K"}]}],"isGlobal":0,"name":"doudizhu_ske","version":"5.0"}